Workbook

Sheet Premissas
A1: KINETIC · Precificação
A2: Edite só as células AMARELAS (texto azul). Todo o resto se recalcula sozinho.
A3: Legenda: amarelo/azul = você preenche · preto = fórmula · verde = vem de outra aba. Valores de exemplo já preenchidos.
A5: Câmbio
A6: Dólar (R$ por US$) | B6: 5.5 | D6: Atualize pelo câmbio do dia + IOF do cartão (~3,5%).
A8: Custos fixos de infraestrutura
A9: Item | B9: Valor mensal (R$) | C9: Valor de entrada | D9: Como é cobrado
A10: Supabase Pro (banco e arquivos) | B10: =C10*IF(LEFT(D10,3)="USD",Premissas!$B$6,1)/IF(RIGHT(D10,3)="ano",12,1) | C10: 25 | D10: USD/mês
A11: Claude Max 5x (desenvolvimento) | B11: =C11*IF(LEFT(D11,3)="USD",Premissas!$B$6,1)/IF(RIGHT(D11,3)="ano",12,1) | C11: 550 | D11: BRL/mês
A12: StayCloud VPS (servidor da API) | B12: =C12*IF(LEFT(D12,3)="USD",Premissas!$B$6,1)/IF(RIGHT(D12,3)="ano",12,1) | C12: 76.5 | D12: BRL/mês
A13: Resend Pro (e-mails) | B13: =C13*IF(LEFT(D13,3)="USD",Premissas!$B$6,1)/IF(RIGHT(D13,3)="ano",12,1) | C13: 20 | D13: USD/mês
A14: Apple Developer (App Store) | B14: =C14*IF(LEFT(D14,3)="USD",Premissas!$B$6,1)/IF(RIGHT(D14,3)="ano",12,1) | C14: 99 | D14: USD/ano
A15: Domínio | B15: =C15*IF(LEFT(D15,3)="USD",Premissas!$B$6,1)/IF(RIGHT(D15,3)="ano",12,1) | C15: 40 | D15: BRL/ano
A16: Contador online | B16: =C16*IF(LEFT(D16,3)="USD",Premissas!$B$6,1)/IF(RIGHT(D16,3)="ano",12,1) | C16: 200 | D16: BRL/mês
A17: Total de custos fixos por mês | B17: =SUM(B10:B16)
A18: Na coluna D use: USD/mês, USD/ano, BRL/mês ou BRL/ano. Google Play (US$ 25 único) fica fora: é pago uma vez só.
A20: Você
A21: Pró-labore desejado (bruto) | B21: 2500 | C21: por mês | D21: Seu salário. Fase 1 = 2.500 · Fase 2 = 5.000.
A22: INSS sobre o pró-labore | B22: 0.11 | D22: Descontado de você (11%).
A23: Margem de lucro desejada | B23: 0.2 | D23: Vai para reserva de caixa e reinvestimento.
A25: Impostos e taxas (Simples Nacional)
A26: Alíquota Anexo III (com Fator R) | B26: 0.06 | D26: Faixa inicial, até R$ 180 mil de faturamento em 12 meses.
A27: Alíquota Anexo V (sem Fator R) | B27: 0.155 | D27: Vale se o pró-labore ficar abaixo de 28% da receita.
A28: Fator R mínimo | B28: 0.28 | D28: Pró-labore ÷ receita precisa ser ≥ 28%.
A29: Taxa do meio de pagamento | B29: 0.03 | D29: Pix/boleto/cartão no Asaas, média aproximada.
A30: Confirme alíquotas e enquadramento (CNAE 6203-1/00 ou 6311-9/00) com o contador.
A32: Preços do Kinetic
A33: Rede: preço por aluno ativo | B33: 3 | C33: por mês | D33: Hipótese a validar no piloto (R$ 2 a R$ 4).
A34: Rede: alunos ativos por unidade | B34: 1000 | D34: Média por academia.
A35: Personal: plano Pro | B35: 49.9 | C35: por mês
A36: Personal: plano Base | B36: 14.9 | C36: por mês

Sheet Meta
A1: Quanto precisa entrar por mês
A2: Calculado a partir da aba Premissas. Não edite aqui.
A4: Receita mínima
A5: Custos fixos | B5: =Premissas!$B$17
A6: Pró-labore | B6: =Premissas!$B$21
A7: Impostos + taxas (% da receita) | B7: =Premissas!$B$26+Premissas!$B$29 | D7: Considera Anexo III (Fator R atendido).
A8: Margem desejada (% da receita) | B8: =Premissas!$B$23
A9: RECEITA MENSAL NECESSÁRIA | B9: =(B5+B6)/(1-B7-B8) | D9: (custos fixos + pró-labore) ÷ (1 − impostos − taxas − margem)
A10: Receita anual equivalente | B10: =B9*12
A11: Fator R (pró-labore ÷ receita) | B11: =IFERROR(B6/B9,0)
A12: Fator R atendido? | B12: =IF(B11>=Premissas!$B$28,"SIM · paga Anexo III","NÃO · aumente o pró-labore")
A14: Isso equivale a (só uma fonte de receita por linha)
A15: Alunos ativos em redes | B15: =ROUNDUP(B9/Premissas!$B$33,0) | C15: alunos
A16: Unidades de academia | B16: =ROUNDUP(B9/(Premissas!$B$33*Premissas!$B$34),0) | C16: unidades
A17: Personais no plano Pro | B17: =ROUNDUP(B9/Premissas!$B$35,0) | C17: personais
A18: Personais no plano Base | B18: =ROUNDUP(B9/Premissas!$B$36,0) | C18: personais
A20: O que chega no seu bolso
A21: Pró-labore bruto | B21: =Premissas!$B$21
A22: (−) INSS | B22: =-Premissas!$B$21*Premissas!$B$22
A23: Pró-labore líquido | B23: =B21+B22 | D23: IR isento até R$ 5 mil/mês a partir de 2026 (confirme com o contador).
A24: Margem que fica na empresa | B24: =B9*Premissas!$B$23 | D24: Reserva de caixa primeiro; depois pode ser distribuída a você sem INSS.

Sheet Simulação
A1: Simulador: e se eu tiver...
A2: Preencha os amarelos com clientes reais ou imaginados e veja o resultado.
A4: Clientes
A5: Unidades de academia | B5: 2 | D5: Ex.: a rede do piloto.
A6: Alunos ativos por unidade | B6: =Premissas!$B$34 | D6: Vem das Premissas; pode sobrescrever.
A7: Preço por aluno ativo | B7: =Premissas!$B$33
A8: Desconto de fundadora | B8: 0.5 | D8: Ex.: 50% nos 12 primeiros meses.
A9: Personais no plano Pro | B9: 20
A10: Personais no plano Base | B10: 30
A12: Resultado do mês
A13: Receita de redes | B13: =B5*B6*B7*(1-B8)
A14: Receita de personais | B14: =B9*Premissas!$B$35+B10*Premissas!$B$36
A15: RECEITA TOTAL | B15: =B13+B14
A16: Fator R | B16: =IFERROR(Premissas!$B$21/B15,0) | D16: Se receita for zero, mostra 0.
A17: Alíquota aplicada | B17: =IF(B16>=Premissas!$B$28,Premissas!$B$26,Premissas!$B$27) | D17: Anexo III se Fator R ≥ 28%, senão Anexo V.
A18: (−) Impostos | B18: =-B15*B17
A19: (−) Taxas de pagamento | B19: =-B15*Premissas!$B$29
A20: (−) Custos fixos | B20: =-Premissas!$B$17
A21: (−) Seu pró-labore | B21: =-Premissas!$B$21
A22: LUCRO DA EMPRESA | B22: =SUM(B18:B21)+B15
A23: Margem de lucro | B23: =IFERROR(B22/B15,0)
A24: Situação | B24: =IF(B22<0,"PREJUÍZO · ainda não paga seu pró-labore",IF(B23<Premissas!$B$23,"Paga você, mas abaixo da margem desejada","META ATINGIDA"))
A25: Falta para a meta | B25: =MAX(0,Meta!B9-B15) | D25: Receita que ainda falta para a aba Meta.
